Examples/TestCifarDataset.py
Examples/TestDIYDataset.py
Examples/TestMNISTDataset.py
Examples/TestModels-Cifar10.py
Examples/TestModels-MNIST.py
Examples/__init__.py
mxbox/DataLoader.py
mxbox/Dataset.py
mxbox/__init__.py
mxbox/sampler.py
mxbox/torchloader.py
mxbox/utils.py
mxbox/datasets/__init__.py
mxbox/datasets/cifar.py
mxbox/datasets/mnist.py
mxbox/datasets/utils.py
mxbox/models/__init__.py
mxbox/models/alexnet.py
mxbox/models/resnet.py
mxbox/models/vgg.py
mxbox/transforms/__init__.py
mxbox/transforms/general.py
mxbox/transforms/mxnetTool.py
mxbox/transforms/numpyTool.py
mxbox/transforms/torchTool.py
mxbox-0.0.22.dist-info/DESCRIPTION.rst
mxbox-0.0.22.dist-info/METADATA
mxbox-0.0.22.dist-info/RECORD
mxbox-0.0.22.dist-info/WHEEL
mxbox-0.0.22.dist-info/metadata.json
mxbox-0.0.22.dist-info/top_level.txt
mxbox-0.0.22.dist-info/zip-safe
