Metadata-Version: 2.0
Name: mxbox
Version: 0.0.22
Summary: Image and video datasets and models for mxnet deep learning
Home-page: https://github.com/lyken17/mxbox
Author: Lyken from TuSimple
Author-email: lykensyu+github@gmail.com
License: BSD
Platform: UNKNOWN
Requires-Dist: numpy
Requires-Dist: pillow
Requires-Dist: six
